xmlrpcutils/__init__.py
xmlrpcutils/server.py
xmlrpcutils/service.py
xmlrpcutils-0.5.1.dist-info/licenses/LICENSE
xmlrpcutils-0.5.1.dist-info/METADATA
xmlrpcutils-0.5.1.dist-info/WHEEL
xmlrpcutils-0.5.1.dist-info/entry_points.txt
xmlrpcutils-0.5.1.dist-info/top_level.txt
xmlrpcutils-0.5.1.dist-info/RECORD
