Metadata-Version: 2.4
Name: xmlrpcutils
Version: 0.5.1
Summary: XML-RPC Server Simplification.
Author: rRR0VrFP
Maintainer: rRR0VrFP
License: MIT
Keywords: xmlrpc
Classifier: Development Status :: 5 - Production/Stable
Classifier: Intended Audience :: Developers
Classifier: Topic :: Software Development :: Libraries :: Python Modules
Classifier: License :: OSI Approved :: MIT License
Classifier: Programming Language :: Python :: 3
Classifier: Programming Language :: Python :: 3 :: Only
License-File: LICENSE
Requires-Dist: magic-import
Requires-Dist: daemon-application>=0.5.6
Requires-Dist: zenutils>=0.3.12
Dynamic: author
Dynamic: classifier
Dynamic: description
Dynamic: description-content-type
Dynamic: keywords
Dynamic: license
Dynamic: license-file
Dynamic: maintainer
Dynamic: requires-dist
Dynamic: summary
